topsis_kartik/topsis.py
TOPSIS_Kartik_101803671-2.1.0.dist-info/License.txt
TOPSIS_Kartik_101803671-2.1.0.dist-info/METADATA
TOPSIS_Kartik_101803671-2.1.0.dist-info/WHEEL
TOPSIS_Kartik_101803671-2.1.0.dist-info/entry_points.txt
TOPSIS_Kartik_101803671-2.1.0.dist-info/top_level.txt
TOPSIS_Kartik_101803671-2.1.0.dist-info/RECORD
