Metadata-Version: 2.1
Name: TOPSIS-Kartik-101803671
Version: 2.1.0
Summary: A Python package to get TOPSIS result of any data.
Home-page: https://github.com/ksharma0408/TOPSIS-Kartik-101803671
Author: Kartik Sharma
Author-email: sharma.kartik0408@gmail.com
License: MIT
Platform: UNKNOWN
Classifier: License :: OSI Approved :: MIT License
Classifier: Programming Language :: Python :: 3
Classifier: Programming Language :: Python :: 3.7
Classifier: Programming Language :: Python :: 3.6
Requires-Dist: pandas
Requires-Dist: numpy
Requires-Dist: scipy
